parsync/__init__.py
parsync-0.1.0.dist-info/LICENSE.txt
parsync-0.1.0.dist-info/METADATA
parsync-0.1.0.dist-info/WHEEL
parsync-0.1.0.dist-info/entry_points.txt
parsync-0.1.0.dist-info/top_level.txt
parsync-0.1.0.dist-info/RECORD
