Metadata-Version: 2.1
Name: parsync
Version: 0.1.0
Summary: Recursively copy missing files to a directory
Author-email: Nicolas Granger <nicolas.granger@cea.fr>
License: CECILL-C
Classifier: License :: CeCILL-C Free Software License Agreement (CECILL-C)
Classifier: Topic :: System :: Clustering
Classifier: Topic :: System :: Filesystems
Classifier: Topic :: System :: Archiving :: Mirroring
Classifier: Topic :: Scientific/Engineering
Requires-Python: >=3.7
License-File: LICENSE.txt
